odoo/addons/agreement_tier_validation/README.rst
odoo/addons/agreement_tier_validation/__init__.py
odoo/addons/agreement_tier_validation/__manifest__.py
odoo/addons/agreement_tier_validation/i18n/agreement_tier_validation.pot
odoo/addons/agreement_tier_validation/models/__init__.py
odoo/addons/agreement_tier_validation/models/agreement.py
odoo/addons/agreement_tier_validation/models/tier_definition.py
odoo/addons/agreement_tier_validation/readme/CONFIGURE.rst
odoo/addons/agreement_tier_validation/readme/CONTRIBUTORS.rst
odoo/addons/agreement_tier_validation/readme/DESCRIPTION.rst
odoo/addons/agreement_tier_validation/readme/INSTALL.rst
odoo/addons/agreement_tier_validation/readme/USAGE.rst
odoo/addons/agreement_tier_validation/static/description/icon.png
odoo/addons/agreement_tier_validation/static/description/index.html
odoo/addons/agreement_tier_validation/tests/__init__.py
odoo/addons/agreement_tier_validation/tests/test_tier_validation.py
odoo/addons/agreement_tier_validation/views/agreement_view.xml
odoo14_addon_agreement_tier_validation-14.0.1.0.1.dist-info/METADATA
odoo14_addon_agreement_tier_validation-14.0.1.0.1.dist-info/WHEEL
odoo14_addon_agreement_tier_validation-14.0.1.0.1.dist-info/top_level.txt
odoo14_addon_agreement_tier_validation-14.0.1.0.1.dist-info/RECORD
